imio/dummypackage/__init__.py
imio/dummypackage/configure.zcml
imio/dummypackage/interfaces.py
imio/dummypackage/profiles.zcml
imio/dummypackage/testing.py
imio/dummypackage/browser/__init__.py
imio/dummypackage/browser/basic.pt
imio/dummypackage/browser/configure.zcml
imio/dummypackage/profiles/default/browserlayer.xml
imio/dummypackage/profiles/default/metadata.xml
imio/dummypackage/profiles/default/registry/main.xml
imio/dummypackage/profiles/default/registry/plone.base.interfaces.controlpanel.IMailSchema.xml
imio/dummypackage/profiles/default/registry/plone.base.interfaces.controlpanel.ISiteSchema.xml
imio/dummypackage/profiles/default/registry/plone.i18n.interfaces.ILanguageSchema.xml
imio/dummypackage/profiles/uninstall/browserlayer.xml
imio_dummypackage-0.0.2.dist-info/METADATA
imio_dummypackage-0.0.2.dist-info/WHEEL
imio_dummypackage-0.0.2.dist-info/entry_points.txt
imio_dummypackage-0.0.2.dist-info/RECORD
